coding2.py
turing2.py
turing_coding2-0.1.dist-info/METADATA
turing_coding2-0.1.dist-info/WHEEL
turing_coding2-0.1.dist-info/top_level.txt
turing_coding2-0.1.dist-info/RECORD
