Metadata-Version: 2.1
Name: turing-coding2
Version: 0.1
Summary: Guangzhou Turing EasyCoding2
Home-page: UNKNOWN
Author: isande
Author-email: isande@qq.com
License: UNKNOWN
Platform: UNKNOWN
Requires-Dist: pygame ==2.1.2
Requires-Dist: Pillow ==9.3.0
